{
  "transitions": [
    {
      "step": "plan",
      "substep": null,
      "from": null,
      "by": "extension",
      "at": "2026-04-16T04:59:05.690Z"
    },
    {
      "step": "plan",
      "substep": null,
      "from": {
        "step": "plan",
        "substep": null
      },
      "by": "extension",
      "at": "2026-04-29T04:33:56.704Z"
    }
  ],
  "currentStep": "plan",
  "stepHistory": {
    "plan": {
      "startedAt": "2026-04-16T04:59:05.689Z",
      "completedAt": null
    }
  },
  "status": "completed",
  "specName": "Custom 404 Page",
  "workflow": "speckit",
  "branch": ""
}